jsonreadwrite/__init__.py
jsonreadwrite/jsonreadwrite.py
jsonreadwrite-1.0.0.dist-info/LICENSE
jsonreadwrite-1.0.0.dist-info/METADATA
jsonreadwrite-1.0.0.dist-info/WHEEL
jsonreadwrite-1.0.0.dist-info/top_level.txt
jsonreadwrite-1.0.0.dist-info/RECORD
