Metadata-Version: 2.1
Name: jsonreadwrite
Version: 1.0.0
Summary: A package to read and write json files
Home-page: https://github.com/Sumiza/jsonreadwrite/
Author: Sumiza
Author-email: sumiza@gmail.com
Project-URL: Bug Tracker, https://github.com/Sumiza/jsonreadwrite/issues
Classifier: Programming Language :: Python :: 3.9
Classifier: Programming Language :: Python :: 3.10
Classifier: License :: OSI Approved :: MIT License
Classifier: Operating System :: OS Independent
Requires-Python: >=3.9
License-File: LICENSE
